<?xml version="1.0" encoding="utf-8"?>
<!--Created with LibraryBuilder for FLAKit -->
<!--http://www.thaumaturgistgames.com/FLAKit-->
<library>
    <images>
        <image>bolt.png</image>
        <image>crosshair.png</image>
        <image>enemy.png</image>
        <image>fighterAtkWalk.png</image>
        <image>fireballShot.png</image>
        <image>horizontal.png</image>
        <image>icicle.png</image>
        <image>lightningBolt.png</image>
        <image>mageAtkWalk.png</image>
        <image>mageWalk.png</image>
        <image>rogue.png</image>
        <image>rogueAtkWalk.png</image>
        <image>shuriken.png</image>
    </images>
    <sounds />
</library>